[
  {"en":"a","jp":"ア"},{"en":"i","jp":"イ"},{"en":"u","jp":"ウ"},{"en":"e","jp":"エ"},{"en":"o","jp":"オ"},
  {"en":"ka","jp":"カ"},{"en":"ki","jp":"キ"},{"en":"ku","jp":"ク"},{"en":"ke","jp":"ケ"},{"en":"ko","jp":"コ"},
  {"en":"sa","jp":"サ"},{"en":"shi","jp":"シ"},{"en":"su","jp":"ス"},{"en":"se","jp":"セ"},{"en":"so","jp":"ソ"},
  {"en":"ta","jp":"タ"},{"en":"chi","jp":"チ"},{"en":"tsu","jp":"ツ"},{"en":"te","jp":"テ"},{"en":"to","jp":"ト"},
  {"en":"na","jp":"ナ"},{"en":"ni","jp":"ニ"},{"en":"nu","jp":"ヌ"},{"en":"ne","jp":"ネ"},{"en":"no","jp":"ノ"},
  {"en":"ha","jp":"ハ"},{"en":"hi","jp":"ヒ"},{"en":"fu","jp":"フ"},{"en":"he","jp":"ヘ"},{"en":"ho","jp":"ホ"},
  {"en":"ma","jp":"マ"},{"en":"mi","jp":"ミ"},{"en":"mu","jp":"ム"},{"en":"me","jp":"メ"},{"en":"mo","jp":"モ"},
  {"en":"ya","jp":"ヤ"},{"en":"i","jp":"イ"},{"en":"yu","jp":"ユ"},{"en":"e","jp":"エ"},{"en":"yo","jp":"ヨ"},
  {"en":"ra","jp":"ラ"},{"en":"ri","jp":"リ"},{"en":"ru","jp":"ル"},{"en":"re","jp":"レ"},{"en":"ro","jp":"ロ"},
  {"en":"wa","jp":"ワ"},{"en":"i","jp":"イ"},{"en":"u","jp":"ウ"},{"en":"e","jp":"エ"},{"en":"o","jp":"オ"},
  {"en":"n","jp":"ン"}
]
